aioredis_lock/__init__.py
aioredis_lock/errors.py
aioredis_lock/locks.py
aioredis_lock/lua_scripts.py
aioredis_lock-0.1.0.dist-info/LICENSE
aioredis_lock-0.1.0.dist-info/METADATA
aioredis_lock-0.1.0.dist-info/WHEEL
aioredis_lock-0.1.0.dist-info/top_level.txt
aioredis_lock-0.1.0.dist-info/RECORD
