Metadata-Version: 2.1
Name: aioredis-lock
Version: 0.1.0
Summary: Wrapper to provide distributed locks in aioredis
Home-page: https://github.com/mrasband/aioredis-lock
Author: Matt Rasband
Author-email: matt.rasband@gmail.com
License: UNKNOWN
Keywords: aioredis,redis,locking,distributed,asyncio
Platform: UNKNOWN
Classifier: Development Status :: 4 - Beta
Classifier: License :: OSI Approved :: MIT License
Classifier: Programming Language :: Python
Classifier: Programming Language :: Python :: 3
Classifier: Programming Language :: Python :: 3.7
Classifier: Programming Language :: Python :: 3.8
Classifier: Programming Language :: Python :: Implementation :: CPython
Requires-Python: >=3.7
Requires-Dist: aioredis
